decparsing/__init__.py
decparsing/_version.py
decparsing/config.py
decparsing/dataHandler.py
decparsing/helpers.py
decparsing/stopwords.txt
decparsing/utils.py
decparsing/analysis/__init__.py
decparsing/analysis/analysisClient.py
decparsing/analysis/analysisJarClient.py
decparsing/analysis/analysisLocalClient.py
decparsing/analysis/analysisRuntimeClient.py
decparsing/analysis/dataClient.py
decparsing/models/__init__.py
decparsing/models/analyze/__init__.py
decparsing/models/analyze/v1/__init__.py
decparsing/models/analyze/v1/analyze_pb2.py
decparsing/models/analyze/v1/analyze_pb2_grpc.py
decparsing/models/analyze/v2/__init__.py
decparsing/models/analyze/v2/analyze_pb2.py
decparsing/models/analyze/v2/analyze_pb2_grpc.py
decparsing/models/analyze/v3/__init__.py
decparsing/models/analyze/v3/analyze_pb2.py
decparsing/models/analyze/v3/analyze_pb2_grpc.py
decparsing/models/parse/__init__.py
decparsing/models/parse/v2/__init__.py
decparsing/models/parse/v2/parse_pb2.py
decparsing/models/parse/v2/parse_pb2_grpc.py
decparsing/parsers/__init__.py
decparsing/parsers/semParser.py
decparsing/parsers/structParser.py
decparsing/parsers/tfidfTransformer.py
decparsing-1.6.1.dist-info/licenses/LICENSE
decparsing-1.6.1.dist-info/METADATA
decparsing-1.6.1.dist-info/WHEEL
decparsing-1.6.1.dist-info/top_level.txt
decparsing-1.6.1.dist-info/RECORD
