Metadata-Version: 2.4
Name: decparsing
Version: 1.6.1
Summary: Transforms abstract static analysis results into intermediate representations that are often used to suggest a decomposition of a monolithic application into microservices.
Author: Khaled Sellami
License:                                  Apache License
Project-URL: Repository, https://github.com/khaledsellami/decomp-parsing-service
Project-URL: Issues, https://github.com/khaledsellami/decomp-parsing-service/issues
Keywords: decomposition,monolith,microservices,static analysis,refactoring
Classifier: Programming Language :: Python
Classifier: Programming Language :: Python :: 3
Classifier: Topic :: Scientific/Engineering
Classifier: Intended Audience :: Developers
Requires-Python: >=3.9
License-File: LICENSE
Requires-Dist: numpy>=1.23.3
Requires-Dist: pandas>=1.4.4
Requires-Dist: scikit-learn>=1.1.3
Requires-Dist: pyarrow>=8.0.0
Requires-Dist: nltk>=3.6.7
Requires-Dist: grpcio>=1.42.0
Requires-Dist: protobuf>=5.29.1
Dynamic: license-file
